DecoderBot/ChatBot.py
DecoderBot/__init__.py
decoderbot-1.2.1.dist-info/licenses/LICENSE
decoderbot-1.2.1.dist-info/METADATA
decoderbot-1.2.1.dist-info/WHEEL
decoderbot-1.2.1.dist-info/top_level.txt
decoderbot-1.2.1.dist-info/RECORD
